labmesh/__init__.py
labmesh/broker.py
labmesh/client.py
labmesh/databank.py
labmesh/relay.py
labmesh/security.py
labmesh/util.py
labmesh-0.0.0.dev0.dist-info/licenses/LICENSE
labmesh-0.0.0.dev0.dist-info/METADATA
labmesh-0.0.0.dev0.dist-info/WHEEL
labmesh-0.0.0.dev0.dist-info/entry_points.txt
labmesh-0.0.0.dev0.dist-info/top_level.txt
labmesh-0.0.0.dev0.dist-info/RECORD
